patray/__init__.py
patray/__main__.py
patray/icon.svg.template
patray/logging.py
patray/pa.py
patray/qt.py
patray/version.txt
patray-0.1.2.dist-info/METADATA
patray-0.1.2.dist-info/WHEEL
patray-0.1.2.dist-info/top_level.txt
patray-0.1.2.dist-info/RECORD
