Metadata-Version: 2.1
Name: patray
Version: 0.1.2
Summary: UNKNOWN
Home-page: https://github.com/pohmelie/patray
Author: pohmelie
Author-email: multisosnooley@gmail.com
License: MIT
Platform: UNKNOWN
License-File: license.txt
Requires-Dist: addict (==2.2.1)
Requires-Dist: click (==7.1.2)
Requires-Dist: cock (==0.4.0)
Requires-Dist: loguru (==0.5.0)
Requires-Dist: pulsectl (==20.5.1)
Requires-Dist: pyside2 (==5.15.0)
Requires-Dist: pyyaml (==5.3.1)
Requires-Dist: shiboken2 (==5.15.0)
Provides-Extra: dev
Requires-Dist: flake8 ; extra == 'dev'
Requires-Dist: pip-tools ; extra == 'dev'
